phsic/__init__.py
phsic/app.py
phsic/config.py
phsic/encoder.py
phsic/kernel.py
phsic/phsic.py
phsic/utils.py
phsic_cli-0.1.0.dist-info/entry_points.txt
phsic_cli-0.1.0.dist-info/LICENSE
phsic_cli-0.1.0.dist-info/WHEEL
phsic_cli-0.1.0.dist-info/METADATA
phsic_cli-0.1.0.dist-info/RECORD
